appdaemon_testing/__init__.py
appdaemon_testing/hass_driver.py
appdaemon_testing/pytest/__init__.py
appdaemon_testing-0.1.4.dist-info/METADATA
appdaemon_testing-0.1.4.dist-info/WHEEL
appdaemon_testing-0.1.4.dist-info/entry_points.txt
appdaemon_testing-0.1.4.dist-info/top_level.txt
appdaemon_testing-0.1.4.dist-info/RECORD
