Metadata-Version: 2.1
Name: appdaemon-testing
Version: 0.1.4
Summary: Utilities for testing AppDaemon applications
Home-page: https://github.com/nickw444/appdaemon-testing
Author: Nick Whyte
Author-email: nick@nickwhyte.com
License: MIT
Platform: UNKNOWN
Classifier: Framework :: Pytest
Requires-Dist: appdaemon
Provides-Extra: pytest
Requires-Dist: pytest ; extra == 'pytest'
Provides-Extra: test
Requires-Dist: pytest ; extra == 'test'
